LICENSE
MANIFEST.in
README.rst
buildout.cfg
pyproject.toml
requirements.txt
setup.py
version.txt
bob/__init__.py
bob.learn.tensorflow.egg-info/PKG-INFO
bob.learn.tensorflow.egg-info/SOURCES.txt
bob.learn.tensorflow.egg-info/dependency_links.txt
bob.learn.tensorflow.egg-info/entry_points.txt
bob.learn.tensorflow.egg-info/not-zip-safe
bob.learn.tensorflow.egg-info/requires.txt
bob.learn.tensorflow.egg-info/top_level.txt
bob/learn/__init__.py
bob/learn/tensorflow/__init__.py
bob/learn/tensorflow/callbacks.py
bob/learn/tensorflow/layers.py
bob/learn/tensorflow/data/__init__.py
bob/learn/tensorflow/data/generator.py
bob/learn/tensorflow/data/tfrecords.py
bob/learn/tensorflow/losses/__init__.py
bob/learn/tensorflow/losses/balanced_cross_entropy.py
bob/learn/tensorflow/losses/center_loss.py
bob/learn/tensorflow/losses/pixel_wise.py
bob/learn/tensorflow/metrics/__init__.py
bob/learn/tensorflow/metrics/embedding_accuracy.py
bob/learn/tensorflow/metrics/pixel_wise.py
bob/learn/tensorflow/models/__init__.py
bob/learn/tensorflow/models/alexnet.py
bob/learn/tensorflow/models/arcface.py
bob/learn/tensorflow/models/autoencoder_face.py
bob/learn/tensorflow/models/densenet.py
bob/learn/tensorflow/models/discriminator.py
bob/learn/tensorflow/models/embedding_validation.py
bob/learn/tensorflow/models/inception.py
bob/learn/tensorflow/models/inception_resnet_v1.py
bob/learn/tensorflow/models/inception_resnet_v2.py
bob/learn/tensorflow/models/lenet5.py
bob/learn/tensorflow/models/mcae.py
bob/learn/tensorflow/models/mine.py
bob/learn/tensorflow/models/mlp.py
bob/learn/tensorflow/models/msu_patch.py
bob/learn/tensorflow/models/resnet50_modified.py
bob/learn/tensorflow/models/simple_cnn.py
bob/learn/tensorflow/scripts/__init__.py
bob/learn/tensorflow/scripts/datasets_to_tfrecords.py
bob/learn/tensorflow/scripts/fit.py
bob/learn/tensorflow/scripts/keras.py
bob/learn/tensorflow/scripts/tf.py
bob/learn/tensorflow/tests/__init__.py
bob/learn/tensorflow/tests/test_arcface.py
bob/learn/tensorflow/tests/test_dataset.py
bob/learn/tensorflow/tests/test_datasets_to_tfrecords.py
bob/learn/tensorflow/tests/test_mine.py
bob/learn/tensorflow/tests/test_utils.py
bob/learn/tensorflow/tests/data/db_to_tfrecords_config.py
bob/learn/tensorflow/utils/__init__.py
bob/learn/tensorflow/utils/image.py
